specpy/OmasIo.dll
specpy/__init__.py
specpy/_specpy.pyd
specpy/boost_date_time-vc140-mt-1_59.dll
specpy/boost_locale-vc140-mt-1_59.dll
specpy/boost_regex-vc140-mt-1_59.dll
specpy/boost_system-vc140-mt-1_59.dll
specpy/g3logger.dll
specpy/msvcp140.dll
specpy/version.py
specpy/zlib1.dll
specpy-1.2.1.dist-info/DESCRIPTION.rst
specpy-1.2.1.dist-info/METADATA
specpy-1.2.1.dist-info/RECORD
specpy-1.2.1.dist-info/WHEEL
specpy-1.2.1.dist-info/metadata.json
specpy-1.2.1.dist-info/top_level.txt
