Metadata-Version: 2.0
Name: specpy
Version: 1.2.1
Summary: Python Interface for Imspector
Home-page: https://imspector.mpibpc.mpg.de/documentation/specpy.html
Author: Bjoern Thiel
Author-email: bjoern.thiel@mpibpc.mpg.de
License: BSD
